balautil/__init__.py
balautil/datastructures.py
balautil/dictutils.py
balautil/downloadutil.py
balautil/plotlyutils.py
balautil/requestutil.py
balautil/wordcloudutil.py
balautil-0.1.5.dist-info/DESCRIPTION.rst
balautil-0.1.5.dist-info/METADATA
balautil-0.1.5.dist-info/RECORD
balautil-0.1.5.dist-info/WHEEL
balautil-0.1.5.dist-info/metadata.json
balautil-0.1.5.dist-info/top_level.txt
