Metadata-Version: 2.0
Name: balautil
Version: 0.1.5
Summary: A simple utililty package of my everyday task
Home-page: https://github.com/balaprasanna/balautil
Author: Bala Prasanna
Author-email: balaprasannav2009@gmail.com
License: UNKNOWN
Platform: UNKNOWN
Classifier: Programming Language :: Python :: 3
Classifier: License :: OSI Approved :: MIT License
Classifier: Operating System :: OS Independent
Requires-Dist: plotly
Requires-Dist: requests
Requires-Dist: wordcloud
